setup.py
unipy_logger/__init__.py
unipy_logger/uni_logger.py
unipy_logger.egg-info/PKG-INFO
unipy_logger.egg-info/SOURCES.txt
unipy_logger.egg-info/dependency_links.txt
unipy_logger.egg-info/not-zip-safe
unipy_logger.egg-info/requires.txt
unipy_logger.egg-info/top_level.txt