Metadata-Version: 1.0
Name: unipy-logger
Version: 0.1.8
Summary: enforce uniplaces log standards and respect uniplaces logging interface.
Home-page: https://github.com/uniplaces/unipy_logger
Author: Raffaello De Pieri
Author-email: raffaello.pieri@uniplaces.com
License: MIT
Keywords: log,json,uniplaces
Platform: UNKNOWN
